tests/__init__.py
tests/conftest.py
tests/test_document.py
tests/test_filter.py
tests/test_formulas.py
text_grade/__init__.py
text_grade/_logger.py
text_grade/document.py
text_grade/filter.py
text_grade/formulas.py
text_grade/grade.py
text_grade/plot.py
text_grade/score.py
text_grade-0.2.0.dist-info/LICENSE
text_grade-0.2.0.dist-info/METADATA
text_grade-0.2.0.dist-info/WHEEL
text_grade-0.2.0.dist-info/top_level.txt
text_grade-0.2.0.dist-info/RECORD
