Metadata-Version: 2.1
Name: text-grade
Version: 0.2.0
Summary: A Python tool to assist text analysis.
Home-page: https://github.com/amenezes/text-grade
Author: Alexandre Menezes
Author-email: alexandre.fmenezes@gmail.com
License: Apache-2.0
Project-URL: Documentation, https://github.com/amenezes/text-grade
Project-URL: Code, https://github.com/amenezes/text-grade
Project-URL: Issue tracker, https://github.com/amenezes/text-grade/issues
Project-URL: Changes, https://github.com/amenezes/text-grade/releases
Keywords: "nlp","spacy","natural-language-processing"
Classifier: Development Status :: 5 - Production/Stable
Classifier: Framework :: AsyncIO
Classifier: Intended Audience :: Developers
Classifier: License :: OSI Approved :: Apache Software License
Classifier: Operating System :: OS Independent
Classifier: Programming Language :: Python :: 3 :: Only
Classifier: Programming Language :: Python :: 3.11
Classifier: Programming Language :: Python :: 3.12
Classifier: Programming Language :: Python :: Implementation :: CPython
Classifier: Programming Language :: Python :: Implementation :: PyPy
Classifier: Topic :: Software Development :: Libraries
Requires-Python: >=3.11
License-File: LICENSE
Requires-Dist: pandas >=2.0.1
Requires-Dist: spacy >=3.0.0
Requires-Dist: pyphen >=0.14.0
Provides-Extra: all
Requires-Dist: mkdocs-material ; extra == 'all'
Requires-Dist: seaborn >=0.12.0 ; extra == 'all'
Provides-Extra: docs
Requires-Dist: mkdocs-material ; extra == 'docs'
Provides-Extra: plot
Requires-Dist: seaborn >=0.12.0 ; extra == 'plot'
